{
  "plan": {
    "dialect": "sqlite",
    "tables": [
      {
        "table": "payments",
        "columns": [
          {
            "name": "id",
            "type": "bigint",
            "isPrimaryKey": true,
            "isUnique": false,
            "isNullable": false,
            "hasDefault": false
          },
          {
            "name": "amount",
            "type": "float",
            "isPrimaryKey": false,
            "isUnique": false,
            "isNullable": true,
            "hasDefault": false
          },
          {
            "name": "method",
            "type": "string",
            "isPrimaryKey": false,
            "isUnique": false,
            "isNullable": true,
            "hasDefault": false
          },
          {
            "name": "status",
            "type": "string",
            "isPrimaryKey": false,
            "isUnique": false,
            "isNullable": true,
            "hasDefault": false
          },
          {
            "name": "currency",
            "type": "string",
            "isPrimaryKey": false,
            "isUnique": false,
            "isNullable": true,
            "hasDefault": false
          },
          {
            "name": "reference_number",
            "type": "string",
            "isPrimaryKey": false,
            "isUnique": false,
            "isNullable": true,
            "hasDefault": false
          },
          {
            "name": "card_last_four",
            "type": "string",
            "isPrimaryKey": false,
            "isUnique": false,
            "isNullable": true,
            "hasDefault": false
          },
          {
            "name": "card_brand",
            "type": "string",
            "isPrimaryKey": false,
            "isUnique": false,
            "isNullable": true,
            "hasDefault": false
          },
          {
            "name": "billing_email",
            "type": "string",
            "isPrimaryKey": false,
            "isUnique": false,
            "isNullable": true,
            "hasDefault": false
          },
          {
            "name": "transaction_id",
            "type": "string",
            "isPrimaryKey": false,
            "isUnique": true,
            "isNullable": true,
            "hasDefault": false
          },
          {
            "name": "payment_provider",
            "type": "string",
            "isPrimaryKey": false,
            "isUnique": false,
            "isNullable": true,
            "hasDefault": false
          },
          {
            "name": "refund_amount",
            "type": "float",
            "isPrimaryKey": false,
            "isUnique": false,
            "isNullable": true,
            "hasDefault": false
          },
          {
            "name": "notes",
            "type": "string",
            "isPrimaryKey": false,
            "isUnique": false,
            "isNullable": true,
            "hasDefault": false
          },
          {
            "name": "booking_id",
            "type": "bigint",
            "isPrimaryKey": false,
            "isUnique": false,
            "isNullable": true,
            "hasDefault": false,
            "references": {
              "table": "bookings",
              "column": "id"
            }
          },
          {
            "name": "customer_id",
            "type": "bigint",
            "isPrimaryKey": false,
            "isUnique": false,
            "isNullable": true,
            "hasDefault": false,
            "references": {
              "table": "customers",
              "column": "id"
            }
          },
          {
            "name": "created_at",
            "type": "datetime",
            "isPrimaryKey": false,
            "isUnique": false,
            "isNullable": false,
            "hasDefault": true,
            "defaultValue": "CURRENT_TIMESTAMP"
          },
          {
            "name": "updated_at",
            "type": "datetime",
            "isPrimaryKey": false,
            "isUnique": false,
            "isNullable": true,
            "hasDefault": false
          },
          {
            "name": "uuid",
            "type": "string",
            "isPrimaryKey": false,
            "isUnique": true,
            "isNullable": true,
            "hasDefault": false
          }
        ],
        "indexes": [
          {
            "name": "payments_transaction_id_unique",
            "columns": [
              "transaction_id"
            ],
            "type": "unique"
          },
          {
            "name": "payments_uuid_unique",
            "columns": [
              "uuid"
            ],
            "type": "unique"
          }
        ]
      },
      {
        "table": "customers",
        "columns": [
          {
            "name": "id",
            "type": "bigint",
            "isPrimaryKey": true,
            "isUnique": false,
            "isNullable": false,
            "hasDefault": false
          },
          {
            "name": "name",
            "type": "string",
            "isPrimaryKey": false,
            "isUnique": false,
            "isNullable": true,
            "hasDefault": false
          },
          {
            "name": "email",
            "type": "string",
            "isPrimaryKey": false,
            "isUnique": true,
            "isNullable": true,
            "hasDefault": false
          },
          {
            "name": "phone",
            "type": "string",
            "isPrimaryKey": false,
            "isUnique": false,
            "isNullable": true,
            "hasDefault": false
          },
          {
            "name": "total_spent",
            "type": "float",
            "isPrimaryKey": false,
            "isUnique": false,
            "isNullable": true,
            "hasDefault": true,
            "defaultValue": 0
          },
          {
            "name": "last_booking",
            "type": "string",
            "isPrimaryKey": false,
            "isUnique": false,
            "isNullable": true,
            "hasDefault": false
          },
          {
            "name": "status",
            "type": "enum",
            "isPrimaryKey": false,
            "isUnique": false,
            "isNullable": true,
            "hasDefault": true,
            "defaultValue": "Active"
          },
          {
            "name": "avatar",
            "type": "string",
            "isPrimaryKey": false,
            "isUnique": false,
            "isNullable": true,
            "hasDefault": false
          },
          {
            "name": "user_id",
            "type": "bigint",
            "isPrimaryKey": false,
            "isUnique": false,
            "isNullable": true,
            "hasDefault": false,
            "references": {
              "table": "users",
              "column": "id"
            }
          },
          {
            "name": "created_at",
            "type": "datetime",
            "isPrimaryKey": false,
            "isUnique": false,
            "isNullable": false,
            "hasDefault": true,
            "defaultValue": "CURRENT_TIMESTAMP"
          },
          {
            "name": "updated_at",
            "type": "datetime",
            "isPrimaryKey": false,
            "isUnique": false,
            "isNullable": true,
            "hasDefault": false
          },
          {
            "name": "uuid",
            "type": "string",
            "isPrimaryKey": false,
            "isUnique": true,
            "isNullable": true,
            "hasDefault": false
          }
        ],
        "indexes": [
          {
            "name": "customers_email_unique",
            "columns": [
              "email"
            ],
            "type": "unique"
          },
          {
            "name": "customers_uuid_unique",
            "columns": [
              "uuid"
            ],
            "type": "unique"
          }
        ]
      },
      {
        "table": "host_profiles",
        "columns": [
          {
            "name": "id",
            "type": "bigint",
            "isPrimaryKey": true,
            "isUnique": false,
            "isNullable": false,
            "hasDefault": false
          },
          {
            "name": "user_id",
            "type": "bigint",
            "isPrimaryKey": false,
            "isUnique": false,
            "isNullable": true,
            "hasDefault": false,
            "references": {
              "table": "users",
              "column": "id"
            }
          },
          {
            "name": "bio",
            "type": "string",
            "isPrimaryKey": false,
            "isUnique": false,
            "isNullable": true,
            "hasDefault": false
          },
          {
            "name": "joined_at",
            "type": "datetime",
            "isPrimaryKey": false,
            "isUnique": false,
            "isNullable": true,
            "hasDefault": false
          },
          {
            "name": "trips",
            "type": "string",
            "isPrimaryKey": false,
            "isUnique": false,
            "isNullable": true,
            "hasDefault": false
          },
          {
            "name": "rating",
            "type": "string",
            "isPrimaryKey": false,
            "isUnique": false,
            "isNullable": true,
            "hasDefault": false
          },
          {
            "name": "response_rate",
            "type": "string",
            "isPrimaryKey": false,
            "isUnique": false,
            "isNullable": true,
            "hasDefault": false
          },
          {
            "name": "response_time",
            "type": "string",
            "isPrimaryKey": false,
            "isUnique": false,
            "isNullable": true,
            "hasDefault": false
          },
          {
            "name": "verified",
            "type": "string",
            "isPrimaryKey": false,
            "isUnique": false,
            "isNullable": true,
            "hasDefault": false
          },
          {
            "name": "all_star",
            "type": "string",
            "isPrimaryKey": false,
            "isUnique": false,
            "isNullable": true,
            "hasDefault": false
          },
          {
            "name": "stripe_account_id",
            "type": "bigint",
            "isPrimaryKey": false,
            "isUnique": false,
            "isNullable": true,
            "hasDefault": false
          },
          {
            "name": "charges_enabled",
            "type": "string",
            "isPrimaryKey": false,
            "isUnique": false,
            "isNullable": true,
            "hasDefault": false
          },
          {
            "name": "payouts_enabled",
            "type": "string",
            "isPrimaryKey": false,
            "isUnique": false,
            "isNullable": true,
            "hasDefault": false
          },
          {
            "name": "platform_fee_bps",
            "type": "float",
            "isPrimaryKey": false,
            "isUnique": false,
            "isNullable": true,
            "hasDefault": false
          },
          {
            "name": "created_at",
            "type": "datetime",
            "isPrimaryKey": false,
            "isUnique": false,
            "isNullable": false,
            "hasDefault": true,
            "defaultValue": "CURRENT_TIMESTAMP"
          },
          {
            "name": "updated_at",
            "type": "datetime",
            "isPrimaryKey": false,
            "isUnique": false,
            "isNullable": true,
            "hasDefault": false
          },
          {
            "name": "uuid",
            "type": "string",
            "isPrimaryKey": false,
            "isUnique": true,
            "isNullable": true,
            "hasDefault": false
          }
        ],
        "indexes": [
          {
            "name": "host_profiles_uuid_unique",
            "columns": [
              "uuid"
            ],
            "type": "unique"
          }
        ]
      },
      {
        "table": "payment_methods",
        "columns": [
          {
            "name": "id",
            "type": "bigint",
            "isPrimaryKey": true,
            "isUnique": false,
            "isNullable": false,
            "hasDefault": false
          },
          {
            "name": "type",
            "type": "string",
            "isPrimaryKey": false,
            "isUnique": false,
            "isNullable": true,
            "hasDefault": false
          },
          {
            "name": "last_four",
            "type": "string",
            "isPrimaryKey": false,
            "isUnique": false,
            "isNullable": true,
            "hasDefault": false
          },
          {
            "name": "brand",
            "type": "string",
            "isPrimaryKey": false,
            "isUnique": false,
            "isNullable": true,
            "hasDefault": false
          },
          {
            "name": "exp_month",
            "type": "float",
            "isPrimaryKey": false,
            "isUnique": false,
            "isNullable": true,
            "hasDefault": false
          },
          {
            "name": "exp_year",
            "type": "float",
            "isPrimaryKey": false,
            "isUnique": false,
            "isNullable": true,
            "hasDefault": false
          },
          {
            "name": "is_default",
            "type": "boolean",
            "isPrimaryKey": false,
            "isUnique": false,
            "isNullable": true,
            "hasDefault": false
          },
          {
            "name": "provider_id",
            "type": "string",
            "isPrimaryKey": false,
            "isUnique": false,
            "isNullable": true,
            "hasDefault": false
          },
          {
            "name": "user_id",
            "type": "bigint",
            "isPrimaryKey": false,
            "isUnique": false,
            "isNullable": true,
            "hasDefault": false,
            "references": {
              "table": "users",
              "column": "id"
            }
          },
          {
            "name": "uuid",
            "type": "string",
            "isPrimaryKey": false,
            "isUnique": true,
            "isNullable": true,
            "hasDefault": false
          }
        ],
        "indexes": [
          {
            "name": "payment_methods_uuid_unique",
            "columns": [
              "uuid"
            ],
            "type": "unique"
          }
        ]
      },
      {
        "table": "cars",
        "columns": [
          {
            "name": "id",
            "type": "bigint",
            "isPrimaryKey": true,
            "isUnique": false,
            "isNullable": false,
            "hasDefault": false
          },
          {
            "name": "slug",
            "type": "string",
            "isPrimaryKey": false,
            "isUnique": true,
            "isNullable": true,
            "hasDefault": false
          },
          {
            "name": "make",
            "type": "string",
            "isPrimaryKey": false,
            "isUnique": false,
            "isNullable": true,
            "hasDefault": false
          },
          {
            "name": "model",
            "type": "string",
            "isPrimaryKey": false,
            "isUnique": false,
            "isNullable": true,
            "hasDefault": false
          },
          {
            "name": "year",
            "type": "float",
            "isPrimaryKey": false,
            "isUnique": false,
            "isNullable": true,
            "hasDefault": false
          },
          {
            "name": "trim",
            "type": "string",
            "isPrimaryKey": false,
            "isUnique": false,
            "isNullable": true,
            "hasDefault": false
          },
          {
            "name": "daily_rate",
            "type": "float",
            "isPrimaryKey": false,
            "isUnique": false,
            "isNullable": true,
            "hasDefault": false
          },
          {
            "name": "original_price",
            "type": "string",
            "isPrimaryKey": false,
            "isUnique": false,
            "isNullable": true,
            "hasDefault": false
          },
          {
            "name": "seats",
            "type": "string",
            "isPrimaryKey": false,
            "isUnique": false,
            "isNullable": true,
            "hasDefault": false
          },
          {
            "name": "doors",
            "type": "string",
            "isPrimaryKey": false,
            "isUnique": false,
            "isNullable": true,
            "hasDefault": false
          },
          {
            "name": "transmission",
            "type": "string",
            "isPrimaryKey": false,
            "isUnique": false,
            "isNullable": true,
            "hasDefault": false
          },
          {
            "name": "fuel_type",
            "type": "string",
            "isPrimaryKey": false,
            "isUnique": false,
            "isNullable": true,
            "hasDefault": false
          },
          {
            "name": "mpg",
            "type": "string",
            "isPrimaryKey": false,
            "isUnique": false,
            "isNullable": true,
            "hasDefault": false
          },
          {
            "name": "range",
            "type": "string",
            "isPrimaryKey": false,
            "isUnique": false,
            "isNullable": true,
            "hasDefault": false
          },
          {
            "name": "category",
            "type": "string",
            "isPrimaryKey": false,
            "isUnique": false,
            "isNullable": true,
            "hasDefault": false
          },
          {
            "name": "description",
            "type": "string",
            "isPrimaryKey": false,
            "isUnique": false,
            "isNullable": true,
            "hasDefault": false
          },
          {
            "name": "image",
            "type": "string",
            "isPrimaryKey": false,
            "isUnique": false,
            "isNullable": true,
            "hasDefault": false
          },
          {
            "name": "license_plate",
            "type": "string",
            "isPrimaryKey": false,
            "isUnique": true,
            "isNullable": true,
            "hasDefault": false
          },
          {
            "name": "vin",
            "type": "string",
            "isPrimaryKey": false,
            "isUnique": true,
            "isNullable": true,
            "hasDefault": false
          },
          {
            "name": "instant_book",
            "type": "string",
            "isPrimaryKey": false,
            "isUnique": false,
            "isNullable": true,
            "hasDefault": false
          },
          {
            "name": "delivery_available",
            "type": "string",
            "isPrimaryKey": false,
            "isUnique": false,
            "isNullable": true,
            "hasDefault": false
          },
          {
            "name": "status",
            "type": "string",
            "isPrimaryKey": false,
            "isUnique": false,
            "isNullable": true,
            "hasDefault": false
          },
          {
            "name": "rating",
            "type": "string",
            "isPrimaryKey": false,
            "isUnique": false,
            "isNullable": true,
            "hasDefault": false
          },
          {
            "name": "review_count",
            "type": "string",
            "isPrimaryKey": false,
            "isUnique": false,
            "isNullable": true,
            "hasDefault": false
          },
          {
            "name": "trips",
            "type": "string",
            "isPrimaryKey": false,
            "isUnique": false,
            "isNullable": true,
            "hasDefault": false
          },
          {
            "name": "badges",
            "type": "string",
            "isPrimaryKey": false,
            "isUnique": false,
            "isNullable": true,
            "hasDefault": false
          },
          {
            "name": "host_profile_id",
            "type": "bigint",
            "isPrimaryKey": false,
            "isUnique": false,
            "isNullable": true,
            "hasDefault": false,
            "references": {
              "table": "host_profiles",
              "column": "id"
            }
          },
          {
            "name": "location_id",
            "type": "bigint",
            "isPrimaryKey": false,
            "isUnique": false,
            "isNullable": true,
            "hasDefault": false,
            "references": {
              "table": "locations",
              "column": "id"
            }
          },
          {
            "name": "created_at",
            "type": "datetime",
            "isPrimaryKey": false,
            "isUnique": false,
            "isNullable": false,
            "hasDefault": true,
            "defaultValue": "CURRENT_TIMESTAMP"
          },
          {
            "name": "updated_at",
            "type": "datetime",
            "isPrimaryKey": false,
            "isUnique": false,
            "isNullable": true,
            "hasDefault": false
          },
          {
            "name": "uuid",
            "type": "string",
            "isPrimaryKey": false,
            "isUnique": true,
            "isNullable": true,
            "hasDefault": false
          }
        ],
        "indexes": [
          {
            "name": "cars_category_location_index",
            "columns": [
              "category",
              "location_id"
            ],
            "type": "index"
          },
          {
            "name": "cars_slug_unique",
            "columns": [
              "slug"
            ],
            "type": "unique"
          },
          {
            "name": "cars_license_plate_unique",
            "columns": [
              "license_plate"
            ],
            "type": "unique"
          },
          {
            "name": "cars_vin_unique",
            "columns": [
              "vin"
            ],
            "type": "unique"
          },
          {
            "name": "cars_uuid_unique",
            "columns": [
              "uuid"
            ],
            "type": "unique"
          }
        ]
      },
      {
        "table": "locations",
        "columns": [
          {
            "name": "id",
            "type": "bigint",
            "isPrimaryKey": true,
            "isUnique": false,
            "isNullable": false,
            "hasDefault": false
          },
          {
            "name": "name",
            "type": "string",
            "isPrimaryKey": false,
            "isUnique": false,
            "isNullable": true,
            "hasDefault": false
          },
          {
            "name": "state",
            "type": "string",
            "isPrimaryKey": false,
            "isUnique": false,
            "isNullable": true,
            "hasDefault": false
          },
          {
            "name": "country",
            "type": "string",
            "isPrimaryKey": false,
            "isUnique": false,
            "isNullable": true,
            "hasDefault": false
          },
          {
            "name": "lat",
            "type": "string",
            "isPrimaryKey": false,
            "isUnique": false,
            "isNullable": true,
            "hasDefault": false
          },
          {
            "name": "lng",
            "type": "string",
            "isPrimaryKey": false,
            "isUnique": false,
            "isNullable": true,
            "hasDefault": false
          },
          {
            "name": "listing_count",
            "type": "string",
            "isPrimaryKey": false,
            "isUnique": false,
            "isNullable": true,
            "hasDefault": false
          },
          {
            "name": "image",
            "type": "string",
            "isPrimaryKey": false,
            "isUnique": false,
            "isNullable": true,
            "hasDefault": false
          },
          {
            "name": "created_at",
            "type": "datetime",
            "isPrimaryKey": false,
            "isUnique": false,
            "isNullable": false,
            "hasDefault": true,
            "defaultValue": "CURRENT_TIMESTAMP"
          },
          {
            "name": "updated_at",
            "type": "datetime",
            "isPrimaryKey": false,
            "isUnique": false,
            "isNullable": true,
            "hasDefault": false
          },
          {
            "name": "uuid",
            "type": "string",
            "isPrimaryKey": false,
            "isUnique": true,
            "isNullable": true,
            "hasDefault": false
          }
        ],
        "indexes": [
          {
            "name": "locations_uuid_unique",
            "columns": [
              "uuid"
            ],
            "type": "unique"
          }
        ]
      },
      {
        "table": "payment_transactions",
        "columns": [
          {
            "name": "id",
            "type": "bigint",
            "isPrimaryKey": true,
            "isUnique": false,
            "isNullable": false,
            "hasDefault": false
          },
          {
            "name": "name",
            "type": "string",
            "isPrimaryKey": false,
            "isUnique": false,
            "isNullable": true,
            "hasDefault": false
          },
          {
            "name": "description",
            "type": "string",
            "isPrimaryKey": false,
            "isUnique": false,
            "isNullable": true,
            "hasDefault": false
          },
          {
            "name": "amount",
            "type": "float",
            "isPrimaryKey": false,
            "isUnique": false,
            "isNullable": true,
            "hasDefault": false
          },
          {
            "name": "type",
            "type": "string",
            "isPrimaryKey": false,
            "isUnique": false,
            "isNullable": true,
            "hasDefault": false
          },
          {
            "name": "provider_id",
            "type": "string",
            "isPrimaryKey": false,
            "isUnique": false,
            "isNullable": true,
            "hasDefault": false
          },
          {
            "name": "user_id",
            "type": "bigint",
            "isPrimaryKey": false,
            "isUnique": false,
            "isNullable": true,
            "hasDefault": false,
            "references": {
              "table": "users",
              "column": "id"
            }
          },
          {
            "name": "payment_method_id",
            "type": "bigint",
            "isPrimaryKey": false,
            "isUnique": false,
            "isNullable": true,
            "hasDefault": false,
            "references": {
              "table": "payment_methods",
              "column": "id"
            }
          },
          {
            "name": "uuid",
            "type": "string",
            "isPrimaryKey": false,
            "isUnique": true,
            "isNullable": true,
            "hasDefault": false
          }
        ],
        "indexes": [
          {
            "name": "payment_transactions_uuid_unique",
            "columns": [
              "uuid"
            ],
            "type": "unique"
          }
        ]
      },
      {
        "table": "reviews",
        "columns": [
          {
            "name": "id",
            "type": "bigint",
            "isPrimaryKey": true,
            "isUnique": false,
            "isNullable": false,
            "hasDefault": false
          },
          {
            "name": "rating",
            "type": "float",
            "isPrimaryKey": false,
            "isUnique": false,
            "isNullable": true,
            "hasDefault": false
          },
          {
            "name": "body",
            "type": "string",
            "isPrimaryKey": false,
            "isUnique": false,
            "isNullable": true,
            "hasDefault": false
          },
          {
            "name": "response",
            "type": "string",
            "isPrimaryKey": false,
            "isUnique": false,
            "isNullable": true,
            "hasDefault": false
          },
          {
            "name": "car_id",
            "type": "bigint",
            "isPrimaryKey": false,
            "isUnique": false,
            "isNullable": true,
            "hasDefault": false,
            "references": {
              "table": "cars",
              "column": "id"
            }
          },
          {
            "name": "booking_id",
            "type": "bigint",
            "isPrimaryKey": false,
            "isUnique": false,
            "isNullable": true,
            "hasDefault": false,
            "references": {
              "table": "bookings",
              "column": "id"
            }
          },
          {
            "name": "user_id",
            "type": "bigint",
            "isPrimaryKey": false,
            "isUnique": false,
            "isNullable": true,
            "hasDefault": false,
            "references": {
              "table": "users",
              "column": "id"
            }
          },
          {
            "name": "created_at",
            "type": "datetime",
            "isPrimaryKey": false,
            "isUnique": false,
            "isNullable": false,
            "hasDefault": true,
            "defaultValue": "CURRENT_TIMESTAMP"
          },
          {
            "name": "updated_at",
            "type": "datetime",
            "isPrimaryKey": false,
            "isUnique": false,
            "isNullable": true,
            "hasDefault": false
          },
          {
            "name": "uuid",
            "type": "string",
            "isPrimaryKey": false,
            "isUnique": true,
            "isNullable": true,
            "hasDefault": false
          }
        ],
        "indexes": [
          {
            "name": "reviews_uuid_unique",
            "columns": [
              "uuid"
            ],
            "type": "unique"
          }
        ]
      },
      {
        "table": "bookings",
        "columns": [
          {
            "name": "id",
            "type": "bigint",
            "isPrimaryKey": true,
            "isUnique": false,
            "isNullable": false,
            "hasDefault": false
          },
          {
            "name": "reference",
            "type": "string",
            "isPrimaryKey": false,
            "isUnique": true,
            "isNullable": true,
            "hasDefault": false
          },
          {
            "name": "car_id",
            "type": "bigint",
            "isPrimaryKey": false,
            "isUnique": false,
            "isNullable": true,
            "hasDefault": false,
            "references": {
              "table": "cars",
              "column": "id"
            }
          },
          {
            "name": "user_id",
            "type": "bigint",
            "isPrimaryKey": false,
            "isUnique": false,
            "isNullable": true,
            "hasDefault": false,
            "references": {
              "table": "users",
              "column": "id"
            }
          },
          {
            "name": "status",
            "type": "string",
            "isPrimaryKey": false,
            "isUnique": false,
            "isNullable": true,
            "hasDefault": false
          },
          {
            "name": "start_date",
            "type": "string",
            "isPrimaryKey": false,
            "isUnique": false,
            "isNullable": true,
            "hasDefault": false
          },
          {
            "name": "end_date",
            "type": "string",
            "isPrimaryKey": false,
            "isUnique": false,
            "isNullable": true,
            "hasDefault": false
          },
          {
            "name": "pickup_time",
            "type": "string",
            "isPrimaryKey": false,
            "isUnique": false,
            "isNullable": true,
            "hasDefault": false
          },
          {
            "name": "return_time",
            "type": "string",
            "isPrimaryKey": false,
            "isUnique": false,
            "isNullable": true,
            "hasDefault": false
          },
          {
            "name": "pickup_location",
            "type": "string",
            "isPrimaryKey": false,
            "isUnique": false,
            "isNullable": true,
            "hasDefault": false
          },
          {
            "name": "delivery_address",
            "type": "string",
            "isPrimaryKey": false,
            "isUnique": false,
            "isNullable": true,
            "hasDefault": false
          },
          {
            "name": "protection_plan",
            "type": "string",
            "isPrimaryKey": false,
            "isUnique": false,
            "isNullable": true,
            "hasDefault": false
          },
          {
            "name": "subtotal",
            "type": "string",
            "isPrimaryKey": false,
            "isUnique": false,
            "isNullable": true,
            "hasDefault": false
          },
          {
            "name": "protection_fee",
            "type": "string",
            "isPrimaryKey": false,
            "isUnique": false,
            "isNullable": true,
            "hasDefault": false
          },
          {
            "name": "extras_fee",
            "type": "string",
            "isPrimaryKey": false,
            "isUnique": false,
            "isNullable": true,
            "hasDefault": false
          },
          {
            "name": "taxes",
            "type": "string",
            "isPrimaryKey": false,
            "isUnique": false,
            "isNullable": true,
            "hasDefault": false
          },
          {
            "name": "total",
            "type": "float",
            "isPrimaryKey": false,
            "isUnique": false,
            "isNullable": true,
            "hasDefault": false
          },
          {
            "name": "platform_fee",
            "type": "string",
            "isPrimaryKey": false,
            "isUnique": false,
            "isNullable": true,
            "hasDefault": false
          },
          {
            "name": "payout_amount",
            "type": "string",
            "isPrimaryKey": false,
            "isUnique": false,
            "isNullable": true,
            "hasDefault": false
          },
          {
            "name": "driver_first_name",
            "type": "string",
            "isPrimaryKey": false,
            "isUnique": false,
            "isNullable": true,
            "hasDefault": false
          },
          {
            "name": "driver_last_name",
            "type": "string",
            "isPrimaryKey": false,
            "isUnique": false,
            "isNullable": true,
            "hasDefault": false
          },
          {
            "name": "driver_email",
            "type": "string",
            "isPrimaryKey": false,
            "isUnique": false,
            "isNullable": true,
            "hasDefault": false
          },
          {
            "name": "driver_phone",
            "type": "string",
            "isPrimaryKey": false,
            "isUnique": false,
            "isNullable": true,
            "hasDefault": false
          },
          {
            "name": "driver_dob",
            "type": "string",
            "isPrimaryKey": false,
            "isUnique": false,
            "isNullable": true,
            "hasDefault": false
          },
          {
            "name": "driver_license",
            "type": "string",
            "isPrimaryKey": false,
            "isUnique": false,
            "isNullable": true,
            "hasDefault": false
          },
          {
            "name": "driver_license_state",
            "type": "string",
            "isPrimaryKey": false,
            "isUnique": false,
            "isNullable": true,
            "hasDefault": false
          },
          {
            "name": "payment_method",
            "type": "string",
            "isPrimaryKey": false,
            "isUnique": false,
            "isNullable": true,
            "hasDefault": false
          },
          {
            "name": "payment_intent_id",
            "type": "bigint",
            "isPrimaryKey": false,
            "isUnique": false,
            "isNullable": true,
            "hasDefault": false
          },
          {
            "name": "cancellation_reason",
            "type": "string",
            "isPrimaryKey": false,
            "isUnique": false,
            "isNullable": true,
            "hasDefault": false
          },
          {
            "name": "created_at",
            "type": "datetime",
            "isPrimaryKey": false,
            "isUnique": false,
            "isNullable": false,
            "hasDefault": true,
            "defaultValue": "CURRENT_TIMESTAMP"
          },
          {
            "name": "updated_at",
            "type": "datetime",
            "isPrimaryKey": false,
            "isUnique": false,
            "isNullable": true,
            "hasDefault": false
          },
          {
            "name": "uuid",
            "type": "string",
            "isPrimaryKey": false,
            "isUnique": true,
            "isNullable": true,
            "hasDefault": false
          }
        ],
        "indexes": [
          {
            "name": "bookings_car_dates_index",
            "columns": [
              "car_id",
              "start_date",
              "end_date"
            ],
            "type": "index"
          },
          {
            "name": "bookings_user_status_index",
            "columns": [
              "user_id",
              "status"
            ],
            "type": "index"
          },
          {
            "name": "bookings_reference_unique",
            "columns": [
              "reference"
            ],
            "type": "unique"
          },
          {
            "name": "bookings_uuid_unique",
            "columns": [
              "uuid"
            ],
            "type": "unique"
          }
        ]
      },
      {
        "table": "coupons",
        "columns": [
          {
            "name": "id",
            "type": "bigint",
            "isPrimaryKey": true,
            "isUnique": false,
            "isNullable": false,
            "hasDefault": false
          },
          {
            "name": "code",
            "type": "string",
            "isPrimaryKey": false,
            "isUnique": true,
            "isNullable": true,
            "hasDefault": false
          },
          {
            "name": "description",
            "type": "string",
            "isPrimaryKey": false,
            "isUnique": false,
            "isNullable": true,
            "hasDefault": false
          },
          {
            "name": "status",
            "type": "enum",
            "isPrimaryKey": false,
            "isUnique": false,
            "isNullable": true,
            "hasDefault": false
          },
          {
            "name": "is_active",
            "type": "boolean",
            "isPrimaryKey": false,
            "isUnique": false,
            "isNullable": true,
            "hasDefault": false
          },
          {
            "name": "discount_type",
            "type": "enum",
            "isPrimaryKey": false,
            "isUnique": false,
            "isNullable": true,
            "hasDefault": false
          },
          {
            "name": "discount_value",
            "type": "float",
            "isPrimaryKey": false,
            "isUnique": false,
            "isNullable": true,
            "hasDefault": false
          },
          {
            "name": "min_order_amount",
            "type": "float",
            "isPrimaryKey": false,
            "isUnique": false,
            "isNullable": true,
            "hasDefault": false
          },
          {
            "name": "max_discount_amount",
            "type": "float",
            "isPrimaryKey": false,
            "isUnique": false,
            "isNullable": true,
            "hasDefault": false
          },
          {
            "name": "usage_limit",
            "type": "float",
            "isPrimaryKey": false,
            "isUnique": false,
            "isNullable": true,
            "hasDefault": false
          },
          {
            "name": "usage_count",
            "type": "float",
            "isPrimaryKey": false,
            "isUnique": false,
            "isNullable": true,
            "hasDefault": false
          },
          {
            "name": "start_date",
            "type": "date",
            "isPrimaryKey": false,
            "isUnique": false,
            "isNullable": true,
            "hasDefault": false
          },
          {
            "name": "end_date",
            "type": "date",
            "isPrimaryKey": false,
            "isUnique": false,
            "isNullable": true,
            "hasDefault": false
          },
          {
            "name": "created_at",
            "type": "datetime",
            "isPrimaryKey": false,
            "isUnique": false,
            "isNullable": false,
            "hasDefault": true,
            "defaultValue": "CURRENT_TIMESTAMP"
          },
          {
            "name": "updated_at",
            "type": "datetime",
            "isPrimaryKey": false,
            "isUnique": false,
            "isNullable": true,
            "hasDefault": false
          },
          {
            "name": "uuid",
            "type": "string",
            "isPrimaryKey": false,
            "isUnique": true,
            "isNullable": true,
            "hasDefault": false
          }
        ],
        "indexes": [
          {
            "name": "coupons_code_unique",
            "columns": [
              "code"
            ],
            "type": "unique"
          },
          {
            "name": "coupons_uuid_unique",
            "columns": [
              "uuid"
            ],
            "type": "unique"
          }
        ]
      },
      {
        "table": "tax_rates",
        "columns": [
          {
            "name": "id",
            "type": "bigint",
            "isPrimaryKey": true,
            "isUnique": false,
            "isNullable": false,
            "hasDefault": false
          },
          {
            "name": "name",
            "type": "string",
            "isPrimaryKey": false,
            "isUnique": false,
            "isNullable": true,
            "hasDefault": false
          },
          {
            "name": "rate",
            "type": "float",
            "isPrimaryKey": false,
            "isUnique": false,
            "isNullable": true,
            "hasDefault": false
          },
          {
            "name": "type",
            "type": "string",
            "isPrimaryKey": false,
            "isUnique": false,
            "isNullable": true,
            "hasDefault": false
          },
          {
            "name": "country",
            "type": "string",
            "isPrimaryKey": false,
            "isUnique": false,
            "isNullable": true,
            "hasDefault": false
          },
          {
            "name": "region",
            "type": "enum",
            "isPrimaryKey": false,
            "isUnique": false,
            "isNullable": true,
            "hasDefault": false
          },
          {
            "name": "status",
            "type": "enum",
            "isPrimaryKey": false,
            "isUnique": false,
            "isNullable": true,
            "hasDefault": true,
            "defaultValue": "active"
          },
          {
            "name": "is_default",
            "type": "boolean",
            "isPrimaryKey": false,
            "isUnique": false,
            "isNullable": true,
            "hasDefault": true,
            "defaultValue": false
          },
          {
            "name": "created_at",
            "type": "datetime",
            "isPrimaryKey": false,
            "isUnique": false,
            "isNullable": false,
            "hasDefault": true,
            "defaultValue": "CURRENT_TIMESTAMP"
          },
          {
            "name": "updated_at",
            "type": "datetime",
            "isPrimaryKey": false,
            "isUnique": false,
            "isNullable": true,
            "hasDefault": false
          },
          {
            "name": "uuid",
            "type": "string",
            "isPrimaryKey": false,
            "isUnique": true,
            "isNullable": true,
            "hasDefault": false
          }
        ],
        "indexes": [
          {
            "name": "tax_rates_uuid_unique",
            "columns": [
              "uuid"
            ],
            "type": "unique"
          }
        ]
      },
      {
        "table": "subscriptions",
        "columns": [
          {
            "name": "id",
            "type": "bigint",
            "isPrimaryKey": true,
            "isUnique": false,
            "isNullable": false,
            "hasDefault": false
          },
          {
            "name": "type",
            "type": "string",
            "isPrimaryKey": false,
            "isUnique": false,
            "isNullable": true,
            "hasDefault": false
          },
          {
            "name": "plan",
            "type": "string",
            "isPrimaryKey": false,
            "isUnique": false,
            "isNullable": true,
            "hasDefault": false
          },
          {
            "name": "provider_id",
            "type": "string",
            "isPrimaryKey": false,
            "isUnique": true,
            "isNullable": true,
            "hasDefault": false
          },
          {
            "name": "provider_status",
            "type": "string",
            "isPrimaryKey": false,
            "isUnique": false,
            "isNullable": true,
            "hasDefault": false
          },
          {
            "name": "unit_price",
            "type": "float",
            "isPrimaryKey": false,
            "isUnique": false,
            "isNullable": true,
            "hasDefault": false
          },
          {
            "name": "provider_type",
            "type": "string",
            "isPrimaryKey": false,
            "isUnique": false,
            "isNullable": true,
            "hasDefault": false
          },
          {
            "name": "provider_price_id",
            "type": "string",
            "isPrimaryKey": false,
            "isUnique": false,
            "isNullable": true,
            "hasDefault": false
          },
          {
            "name": "quantity",
            "type": "float",
            "isPrimaryKey": false,
            "isUnique": false,
            "isNullable": true,
            "hasDefault": false
          },
          {
            "name": "trial_ends_at",
            "type": "datetime",
            "isPrimaryKey": false,
            "isUnique": false,
            "isNullable": true,
            "hasDefault": false
          },
          {
            "name": "ends_at",
            "type": "datetime",
            "isPrimaryKey": false,
            "isUnique": false,
            "isNullable": true,
            "hasDefault": false
          },
          {
            "name": "last_used_at",
            "type": "datetime",
            "isPrimaryKey": false,
            "isUnique": false,
            "isNullable": true,
            "hasDefault": false
          },
          {
            "name": "user_id",
            "type": "bigint",
            "isPrimaryKey": false,
            "isUnique": false,
            "isNullable": true,
            "hasDefault": false,
            "references": {
              "table": "users",
              "column": "id"
            }
          },
          {
            "name": "uuid",
            "type": "string",
            "isPrimaryKey": false,
            "isUnique": true,
            "isNullable": true,
            "hasDefault": false
          }
        ],
        "indexes": [
          {
            "name": "subscriptions_provider_id_unique",
            "columns": [
              "provider_id"
            ],
            "type": "unique"
          },
          {
            "name": "subscriptions_uuid_unique",
            "columns": [
              "uuid"
            ],
            "type": "unique"
          }
        ]
      },
      {
        "table": "users",
        "columns": [
          {
            "name": "id",
            "type": "bigint",
            "isPrimaryKey": true,
            "isUnique": false,
            "isNullable": false,
            "hasDefault": false
          },
          {
            "name": "name",
            "type": "string",
            "isPrimaryKey": false,
            "isUnique": false,
            "isNullable": true,
            "hasDefault": false
          },
          {
            "name": "email",
            "type": "string",
            "isPrimaryKey": false,
            "isUnique": true,
            "isNullable": true,
            "hasDefault": false
          },
          {
            "name": "password",
            "type": "string",
            "isPrimaryKey": false,
            "isUnique": false,
            "isNullable": true,
            "hasDefault": false
          },
          {
            "name": "phone",
            "type": "string",
            "isPrimaryKey": false,
            "isUnique": false,
            "isNullable": true,
            "hasDefault": false
          },
          {
            "name": "date_of_birth",
            "type": "string",
            "isPrimaryKey": false,
            "isUnique": false,
            "isNullable": true,
            "hasDefault": false
          },
          {
            "name": "license_number",
            "type": "string",
            "isPrimaryKey": false,
            "isUnique": false,
            "isNullable": true,
            "hasDefault": false
          },
          {
            "name": "license_state",
            "type": "string",
            "isPrimaryKey": false,
            "isUnique": false,
            "isNullable": true,
            "hasDefault": false
          },
          {
            "name": "avatar_url",
            "type": "string",
            "isPrimaryKey": false,
            "isUnique": false,
            "isNullable": true,
            "hasDefault": false
          },
          {
            "name": "role",
            "type": "string",
            "isPrimaryKey": false,
            "isUnique": false,
            "isNullable": true,
            "hasDefault": false
          },
          {
            "name": "created_at",
            "type": "datetime",
            "isPrimaryKey": false,
            "isUnique": false,
            "isNullable": false,
            "hasDefault": true,
            "defaultValue": "CURRENT_TIMESTAMP"
          },
          {
            "name": "updated_at",
            "type": "datetime",
            "isPrimaryKey": false,
            "isUnique": false,
            "isNullable": true,
            "hasDefault": false
          },
          {
            "name": "uuid",
            "type": "string",
            "isPrimaryKey": false,
            "isUnique": true,
            "isNullable": true,
            "hasDefault": false
          }
        ],
        "indexes": [
          {
            "name": "users_email_name_index",
            "columns": [
              "email",
              "name"
            ],
            "type": "index"
          },
          {
            "name": "users_email_unique",
            "columns": [
              "email"
            ],
            "type": "unique"
          },
          {
            "name": "users_uuid_unique",
            "columns": [
              "uuid"
            ],
            "type": "unique"
          }
        ]
      },
      {
        "table": "extras",
        "columns": [
          {
            "name": "id",
            "type": "bigint",
            "isPrimaryKey": true,
            "isUnique": false,
            "isNullable": false,
            "hasDefault": false
          },
          {
            "name": "code",
            "type": "string",
            "isPrimaryKey": false,
            "isUnique": true,
            "isNullable": true,
            "hasDefault": false
          },
          {
            "name": "name",
            "type": "string",
            "isPrimaryKey": false,
            "isUnique": false,
            "isNullable": true,
            "hasDefault": false
          },
          {
            "name": "description",
            "type": "string",
            "isPrimaryKey": false,
            "isUnique": false,
            "isNullable": true,
            "hasDefault": false
          },
          {
            "name": "price_per_day",
            "type": "float",
            "isPrimaryKey": false,
            "isUnique": false,
            "isNullable": true,
            "hasDefault": false
          },
          {
            "name": "icon",
            "type": "string",
            "isPrimaryKey": false,
            "isUnique": false,
            "isNullable": true,
            "hasDefault": false
          },
          {
            "name": "created_at",
            "type": "datetime",
            "isPrimaryKey": false,
            "isUnique": false,
            "isNullable": false,
            "hasDefault": true,
            "defaultValue": "CURRENT_TIMESTAMP"
          },
          {
            "name": "updated_at",
            "type": "datetime",
            "isPrimaryKey": false,
            "isUnique": false,
            "isNullable": true,
            "hasDefault": false
          },
          {
            "name": "uuid",
            "type": "string",
            "isPrimaryKey": false,
            "isUnique": true,
            "isNullable": true,
            "hasDefault": false
          }
        ],
        "indexes": [
          {
            "name": "extras_code_unique",
            "columns": [
              "code"
            ],
            "type": "unique"
          },
          {
            "name": "extras_uuid_unique",
            "columns": [
              "uuid"
            ],
            "type": "unique"
          }
        ]
      },
      {
        "table": "car_photos",
        "columns": [
          {
            "name": "id",
            "type": "bigint",
            "isPrimaryKey": true,
            "isUnique": false,
            "isNullable": false,
            "hasDefault": false
          },
          {
            "name": "url",
            "type": "string",
            "isPrimaryKey": false,
            "isUnique": false,
            "isNullable": true,
            "hasDefault": false
          },
          {
            "name": "caption",
            "type": "string",
            "isPrimaryKey": false,
            "isUnique": false,
            "isNullable": true,
            "hasDefault": false
          },
          {
            "name": "position",
            "type": "float",
            "isPrimaryKey": false,
            "isUnique": false,
            "isNullable": true,
            "hasDefault": false
          },
          {
            "name": "is_primary",
            "type": "boolean",
            "isPrimaryKey": false,
            "isUnique": false,
            "isNullable": true,
            "hasDefault": false
          },
          {
            "name": "car_id",
            "type": "bigint",
            "isPrimaryKey": false,
            "isUnique": false,
            "isNullable": true,
            "hasDefault": false,
            "references": {
              "table": "cars",
              "column": "id"
            }
          },
          {
            "name": "created_at",
            "type": "datetime",
            "isPrimaryKey": false,
            "isUnique": false,
            "isNullable": false,
            "hasDefault": true,
            "defaultValue": "CURRENT_TIMESTAMP"
          },
          {
            "name": "updated_at",
            "type": "datetime",
            "isPrimaryKey": false,
            "isUnique": false,
            "isNullable": true,
            "hasDefault": false
          },
          {
            "name": "uuid",
            "type": "string",
            "isPrimaryKey": false,
            "isUnique": true,
            "isNullable": true,
            "hasDefault": false
          }
        ],
        "indexes": [
          {
            "name": "car_photos_uuid_unique",
            "columns": [
              "uuid"
            ],
            "type": "unique"
          }
        ]
      }
    ]
  },
  "hash": "fbf21dca85702cc6d752bab6f94d27686a2617d8cb454264cf91f083f7a1ed53",
  "dialect": "sqlite",
  "updatedAt": "2026-04-24T22:01:44.503Z"
}